pip_services4_mysql/__init__.py
pip_services4_mysql/build/DefaultMySqlFactory.py
pip_services4_mysql/build/__init__.py
pip_services4_mysql/connect/MySqlConnection.py
pip_services4_mysql/connect/MySqlConnectionResolver.py
pip_services4_mysql/connect/__init__.py
pip_services4_mysql/persistence/IdentifiableJsonMySqlPersistence.py
pip_services4_mysql/persistence/IdentifiableMySqlPersistence.py
pip_services4_mysql/persistence/MySqlPersistence.py
pip_services4_mysql/persistence/__init__.py
pip_services4_mysql-0.0.1.dist-info/LICENSE
pip_services4_mysql-0.0.1.dist-info/METADATA
pip_services4_mysql-0.0.1.dist-info/WHEEL
pip_services4_mysql-0.0.1.dist-info/top_level.txt
pip_services4_mysql-0.0.1.dist-info/zip-safe
pip_services4_mysql-0.0.1.dist-info/RECORD
